eth_accounts/__init__.py
eth_accounts/account.py
eth_accounts/account_utils.py
eth_accounts-20191227.dist-info/LICENSE
eth_accounts-20191227.dist-info/METADATA
eth_accounts-20191227.dist-info/WHEEL
eth_accounts-20191227.dist-info/top_level.txt
eth_accounts-20191227.dist-info/RECORD
