Metadata-Version: 2.1
Name: eth-accounts
Version: 20191227
Summary: Local Ethereum keystore management library
Home-page: https://github.com/AndreMiras/eth_accounts
Author: Andre Miras
Author-email: 
License: MIT license
Keywords: eth_accounts
Platform: UNKNOWN
Classifier: Development Status :: 2 - Pre-Alpha
Classifier: Intended Audience :: Developers
Classifier: License :: OSI Approved :: MIT License
Classifier: Natural Language :: English
Classifier: Programming Language :: Python :: 3
Classifier: Programming Language :: Python :: 3.6
Classifier: Programming Language :: Python :: 3.7
Classifier: Programming Language :: Python :: 3.8
Requires-Python: >=3.6
Requires-Dist: eth-account (<0.5.0)
Requires-Dist: eth-utils
